{
  "ConfigurationApp": [
    "SnCfgAppSubMenuView",
    "SnCfgBoolParamView",
    "SnCfgCharParamView",
    "SnCfgMenuView",
    "SnCfgNumericParamView",
    "SnCfgStringParamView",
    "SnFnKeyAssignView"
  ],
  "DefaultApp": [
    "SnBarcodeProgressView"
  ],
  "ImageViewerApp": [
    "SnImageViewView"
  ],
  "OutInMatchApp": [
    "SnOutInMatchView"
  ],
  "ScanAndEntQty_DApp": [
    "SnScanAndEntQty_DView"
  ],
  "ScanAndEnterLocApp": [
    "SnScanAndEntLocView"
  ],
  "ScanAndEnterQtyApp": [
    "SnScanAndEntQtyView"
  ],
  "ScanInventoryApp": [
    "SnScanInventoryView"
  ],
  "SettingLeaf": [
    "SnCfgBoolParamView",
    "SnCfgCharParamView",
    "SnCfgNumericParamView",
    "SnCfgStringParamView",
    "SnFnKeyAssignView"
  ],
  "ZebraPlatformScreen": [
    "SnHomeMenuView",
    "SnSplashView"
  ]
}